darksorter/__init__.py
darksorter/__main__.py
darksorter/reader.py
darksorter/writer.py
darksorter-0.1.2.dist-info/LICENSE
darksorter-0.1.2.dist-info/METADATA
darksorter-0.1.2.dist-info/WHEEL
darksorter-0.1.2.dist-info/entry_points.txt
darksorter-0.1.2.dist-info/RECORD
