Metadata-Version: 2.1
Name: darksorter
Version: 0.1.2
Summary: Astrophotography Dark Frame Sorter
License: MIT
Author: Milhan Kim
Requires-Python: >=3.11,<4.0
Classifier: License :: OSI Approved :: MIT License
Classifier: Programming Language :: Python :: 3
Classifier: Programming Language :: Python :: 3.11
Classifier: Programming Language :: Python :: 3.12
Requires-Dist: astropy (<6)
Requires-Dist: python-dateutil (<3)
Requires-Dist: typer[all] (<1)
